nso/__init__.py
nso/__main__.py
nso/api.py
nso/exceptions.py
nso/structures.py
nso/util.py
nso_applet_api-0.0.31.dist-info/LICENSE
nso_applet_api-0.0.31.dist-info/METADATA
nso_applet_api-0.0.31.dist-info/WHEEL
nso_applet_api-0.0.31.dist-info/top_level.txt
nso_applet_api-0.0.31.dist-info/RECORD
