Metadata-Version: 2.1
Name: nso-applet-api
Version: 0.0.31
Summary: Nintendo NSO Applet API
Home-page: https://github.com/MCMi460/nso-applet-api
Author: Deltaion Lee
Author-email: 32529306+MCMi460@users.noreply.github.com
License-File: LICENSE
Requires-Dist: httpx
Requires-Dist: requests
